LICENSE
MANIFEST.in
README.rst
setup.cfg
setup.py
docs/Makefile
docs/source/conf.py
docs/source/flow.rst
docs/source/genindex.rst
docs/source/index.rst
docs/source/yeelight.rst
docs/source/_static/yeelight.jpg
yeelight/__init__.py
yeelight/decorator.py
yeelight/enums.py
yeelight/flow.py
yeelight/flows.py
yeelight/main.py
yeelight/metadata.py
yeelight/ssdp_discover.py
yeelight/tests.py
yeelight/transitions.py
yeelight/utils.py
yeelight/version.py
yeelight_jh.egg-info/PKG-INFO
yeelight_jh.egg-info/SOURCES.txt
yeelight_jh.egg-info/dependency_links.txt
yeelight_jh.egg-info/requires.txt
yeelight_jh.egg-info/top_level.txt