Metadata-Version: 1.2
Name: yeelight-jh
Version: 0.11.1
Summary: A Python library for controlling YeeLight RGB bulbs.
Home-page: https://gitlab.com/stavros/python-yeelight/
Author: Stavros Korokithakis
Author-email: hi@stavros.io
License: BSD
Platform: UNKNOWN
Classifier: License :: OSI Approved :: BSD License
Classifier: Programming Language :: Python
Classifier: Programming Language :: Python :: 3.4
Classifier: Programming Language :: Python :: 3.5
Classifier: Programming Language :: Python :: 3.6
Classifier: Programming Language :: Python :: 3.7
Classifier: Programming Language :: Python :: 3.8
Classifier: Topic :: Software Development :: Libraries :: Python Modules
Requires-Python: >=3.4
